ncps/__init__.py
ncps/datasets/__init__.py
ncps/datasets/icra2020_lidar_collision_avoidance.py
ncps/datasets/utils.py
ncps/datasets/tf/__init__.py
ncps/datasets/tf/atari_cloning.py
ncps/datasets/torch/__init__.py
ncps/datasets/torch/atari_cloning.py
ncps/keras/__init__.py
ncps/keras/cfc.py
ncps/keras/cfc_cell.py
ncps/keras/ltc.py
ncps/keras/ltc_cell.py
ncps/keras/mm_rnn.py
ncps/keras/wired_cfc_cell.py
ncps/paddle/__init__.py
ncps/paddle/ltc_cell.py
ncps/tf/__init__.py
ncps/tf/cfc.py
ncps/tf/cfc_cell.py
ncps/tf/ltc.py
ncps/tf/ltc_cell.py
ncps/tf/mm_rnn.py
ncps/tf/wired_cfc_cell.py
ncps/torch/__init__.py
ncps/torch/cfc.py
ncps/torch/cfc_cell.py
ncps/torch/lstm.py
ncps/torch/ltc.py
ncps/torch/ltc_cell.py
ncps/torch/wired_cfc_cell.py
ncps/wirings/__init__.py
ncps/wirings/wirings.py
ncps-1.0.1.dist-info/LICENSE
ncps-1.0.1.dist-info/METADATA
ncps-1.0.1.dist-info/WHEEL
ncps-1.0.1.dist-info/top_level.txt
ncps-1.0.1.dist-info/RECORD
